{
  "trend_direction": "BEARISH",
  "market_structure": "Acceptance",
  "key_levels": {
    "vPOC": "62045.9",
    "VAL": "61200.0",
    "VAH": "YOK"
  },
  "order_flow_signal": "SELL",
  "confidence_score": "90",
  "entry": "60350",
  "tp1": "60050",
  "tp2": "59800",
  "stop": "60550",
  "absorption": "YOK",
  "dom_observation": "Saticilar baskin, 60450 ve 60500 seviyelerinde buyuk ask (satis) bloklari var. Alim tarafi (bid) zayif.",
  "reasoning": "Fiyat, onceki deger alaninin (VAL) altinda kabul gordu ve basarisiz bir alim denemesinin ardindan gelen guclu negatif delta (-693) ile agresif satis baskisi devam ediyor.",
  "should_trade": "EVET",
  "timestamp": "17:39:23"
}