{
  "trend_direction": "SIDEWAYS",
  "market_structure": "Rejection",
  "key_levels": {
    "vPOC": "61100.0",
    "VAL": "60562.5",
    "VAH": "61452.9"
  },
  "order_flow_signal": "BUY",
  "confidence_score": 85,
  "entry": "60570.0",
  "tp1": "61100.0",
  "tp2": "61450.0",
  "stop": "60420.0",
  "absorption": "VAL seviyesinde (60562.5) net BID absorption gozlemleniyor. Footprint'te buyuk alimlar ve pozitife donen delta, saticilarin absorbe edildigini gosteriyor.",
  "dom_observation": "Fiyatin hemen altinda 60500-60430 arasinda kumeleşmis buyuk bid emirleri (80, 69 lot) destegi guclendiriyor.",
  "reasoning": "Fiyat, kilit destek seviyesi olan VAL'de alici absorpsiyonu ve pozitife donen delta ile net bir sekilde reddedilme (rejection) sinyali veriyor.",
  "should_trade": "EVET",
  "timestamp": "23:35:51"
}