{
  "trend_direction": "SIDEWAYS",
  "market_structure": "Absorption Detected",
  "key_levels": {
    "vPOC": "61311.8",
    "VAL": "61150.0",
    "VAH": "61452.3"
  },
  "order_flow_signal": "BUY",
  "confidence_score": "85",
  "entry": "61310.0",
  "tp1": "61450.0",
  "tp2": "61500.0",
  "stop": "61240.0",
  "absorption": "Aggressive sellers (high negative delta in previous candle) failed to break down and are being absorbed by passive buyers at the vPOC.",
  "dom_observation": "Very large stacked bid wall (2128 lots) at 61300.0 is providing strong support and absorbing selling pressure.",
  "reasoning": "Aggressive sellers are being absorbed by a large passive bid wall at the session vPOC, indicating a high probability of a rotation back up towards the VAH.",
  "should_trade": "EVET",
  "timestamp": "03:44:44"
}