{
  "bias": "BULLISH",
  "signal": "LONG",
  "confidence": "MEDIUM",
  "setup_type": "TEXTBOOK",
  "entry": "63550",
  "tp1": "63600",
  "tp2": "63650",
  "stop": "63520",
  "key_level": "VAL (63550)",
  "absorption": "Fiyat VAL seviyesine düşerken CVD'nin yükselmesi, alıcıların satışları bu seviyede absorbe ettiğini gösteriyor.",
  "dom_observation": "63550 seviyesinde 32 lotluk bir bid duvarı mevcut. 63650 üzerinde ise yoğunlaşan ask duvarları direnç oluşturuyor.",
  "reason": "Fiyat VAL seviyesinde güçlü bir CVD bullish diverjansı gösteriyor; alıcılar düşen fiyatta agresif bir şekilde alım yapıyor. Bu, bir yükseliş dönüşü sinyalidir.",
  "should_trade": "EVET",
  "should_reason": "Fiyat VAL seviyesinde ve CVD düşen fiyata rağmen yükselerek alıcıların absorbe ettiğini gösteriyor, bu da bir tepki beklenmesi gereken kritik bir seviyedir.",
  "timestamp": "19:16:50"
}