{
  "timestamp": "2026-05-11T22:34:20Z",
  "symbol": "NQ",
  "price": 29440.50,
  "total_bid": 32,
  "total_ask": 43,
  "ratio": 42.7,
  "asks": [
    {"price": 29360.00, "volume": 2},
    {"price": 29389.50, "volume": 4},
    {"price": 29415.00, "volume": 4},
    {"price": 29423.75, "volume": 5},
    {"price": 29426.25, "volume": 1},
    {"price": 29426.50, "volume": 4},
    {"price": 29427.00, "volume": 2},
    {"price": 29427.75, "volume": 2},
    {"price": 29429.50, "volume": 12},
    {"price": 29432.00, "volume": 7}
  ],
  "bids": [
    {"price": 29545.00, "volume": 1},
    {"price": 29516.50, "volume": 1},
    {"price": 29516.25, "volume": 1},
    {"price": 29516.00, "volume": 1},
    {"price": 29515.50, "volume": 2},
    {"price": 29480.00, "volume": 14},
    {"price": 29442.75, "volume": 5},
    {"price": 29442.50, "volume": 1},
    {"price": 29442.00, "volume": 2},
    {"price": 29441.75, "volume": 4}
  ]
}